{
  "file": "L09 Agility And Intonation - Cheryl Porter Vocal Method.pdf",
  "note_count": 126,
  "rows": [
    {
      "page": 0,
      "clefY": 170.9,
      "count": 13,
      "midis": [
        71,
        69,
        67,
        69,
        67,
        64,
        67,
        67,
        67,
        67,
        67,
        60,
        59
      ],
      "offsets": [
        0,
        -2,
        -4,
        -2,
        -4,
        -7,
        -4,
        -4,
        -4,
        -4,
        -4,
        -11,
        -12
      ]
    },
    {
      "page": 0,
      "clefY": 234.5,
      "count": 10,
      "midis": [
        71,
        69,
        67,
        69,
        67,
        64,
        67,
        67,
        64,
        67
      ],
      "offsets": [
        0,
        -2,
        -4,
        -2,
        -4,
        -7,
        -4,
        -4,
        -7,
        -4
      ]
    },
    {
      "page": 0,
      "clefY": 408.4,
      "count": 11,
      "midis": [
        76,
        74,
        71,
        71,
        67,
        69,
        71,
        69,
        69,
        67,
        65
      ],
      "offsets": [
        0,
        -2,
        -5,
        -5,
        -9,
        -7,
        -5,
        -7,
        -7,
        -9,
        -11
      ]
    },
    {
      "page": 0,
      "clefY": 465.6,
      "count": 10,
      "midis": [
        76,
        74,
        71,
        71,
        69,
        67,
        67,
        69,
        72,
        71
      ],
      "offsets": [
        0,
        -2,
        -5,
        -5,
        -7,
        -9,
        -9,
        -7,
        -4,
        -5
      ]
    },
    {
      "page": 0,
      "clefY": 639.5,
      "count": 20,
      "midis": [
        64,
        65,
        67,
        69,
        71,
        71,
        69,
        67,
        65,
        64,
        64,
        65,
        67,
        69,
        71,
        71,
        69,
        67,
        65,
        64
      ],
      "offsets": [
        0,
        1,
        3,
        5,
        7,
        7,
        5,
        3,
        1,
        0,
        0,
        1,
        3,
        5,
        7,
        7,
        5,
        3,
        1,
        0
      ]
    },
    {
      "page": 0,
      "clefY": 696.7,
      "count": 15,
      "midis": [
        64,
        65,
        67,
        69,
        71,
        71,
        69,
        67,
        65,
        64,
        64,
        65,
        67,
        69,
        71
      ],
      "offsets": [
        0,
        1,
        3,
        5,
        7,
        7,
        5,
        3,
        1,
        0,
        0,
        1,
        3,
        5,
        7
      ]
    },
    {
      "page": 1,
      "clefY": 130.9,
      "count": 19,
      "midis": [
        73,
        76,
        74,
        72,
        74,
        72,
        69,
        67,
        72,
        69,
        65,
        69,
        67,
        69,
        67,
        62,
        60,
        60,
        60
      ],
      "offsets": [
        0,
        3,
        1,
        -1,
        1,
        -1,
        -4,
        -6,
        -1,
        -4,
        -8,
        -4,
        -6,
        -4,
        -6,
        -11,
        -13,
        -13,
        -13
      ]
    },
    {
      "page": 1,
      "clefY": 281.2,
      "count": 16,
      "midis": [
        59,
        60,
        64,
        65,
        67,
        67,
        67,
        67,
        67,
        67,
        67,
        67,
        65,
        64,
        60,
        59
      ],
      "offsets": [
        0,
        1,
        5,
        6,
        8,
        8,
        8,
        8,
        8,
        8,
        8,
        8,
        6,
        5,
        1,
        0
      ]
    },
    {
      "page": 1,
      "clefY": 341.5,
      "count": 12,
      "midis": [
        59,
        64,
        59,
        65,
        59,
        72,
        71,
        71,
        69,
        67,
        65,
        64
      ],
      "offsets": [
        0,
        5,
        0,
        6,
        0,
        13,
        12,
        12,
        10,
        8,
        6,
        5
      ]
    }
  ],
  "debug": {
    "glyph_hist": {
      "U+F4BE": 125,
      "U+E240": 20,
      "U+E4E6": 9,
      "U+E050": 9,
      "U+E4A3": 7,
      "U+ECA5": 4,
      "U+E08A": 4,
      "U+E4E5": 4,
      "U+E260": 3,
      "U+E4E4": 2,
      "U+E1E7": 2,
      "U+E4C0": 2,
      "U+E5D0": 1,
      "U+E262": 1,
      "U+E0F5": 1,
      "U+E0F6": 1,
      "U+F4BD": 1
    }
  }
}